CHANGES.rst
MANIFEST.in
README.rst
setup.cfg
setup.py
crosscompute_notebook_extensions/__init__.py
crosscompute_notebook_extensions/ipynb.py
crosscompute_notebook_extensions/macros.py
crosscompute_notebook_extensions/settings.py
crosscompute_notebook_extensions.egg-info/PKG-INFO
crosscompute_notebook_extensions.egg-info/SOURCES.txt
crosscompute_notebook_extensions.egg-info/dependency_links.txt
crosscompute_notebook_extensions.egg-info/entry_points.txt
crosscompute_notebook_extensions.egg-info/not-zip-safe
crosscompute_notebook_extensions.egg-info/requires.txt
crosscompute_notebook_extensions.egg-info/top_level.txt
crosscompute_notebook_extensions/assets/tools.js
crosscompute_notebook_extensions/templates/python.jinja2