Metadata-Version: 1.1
Name: crosscompute-notebook-extensions
Version: 0.5.2
Summary: CrossCompute extensions for Jupyter Notebook
Home-page: https://crosscompute.com/docs
Author: CrossCompute Inc
Author-email: support@crosscompute.com
License: UNKNOWN
Keywords: web crosscompute jupyter
Platform: UNKNOWN
Classifier: Framework :: Jupyter
Classifier: Framework :: Pyramid
Classifier: Programming Language :: Python
